bangla_ipa/__init__.py
bangla_ipa/ipa.py
data/__init__.py
data/ipa_vocab_data.csv
model/__init__.py
model/ipa_model.pth
scripts/__init__.py
scripts/translator.py
tests/__init__.py
tests/unit_testing.py
bangla_ipa-1.0.2.dist-info/LICENSE
bangla_ipa-1.0.2.dist-info/METADATA
bangla_ipa-1.0.2.dist-info/WHEEL
bangla_ipa-1.0.2.dist-info/top_level.txt
bangla_ipa-1.0.2.dist-info/RECORD
