Metadata-Version: 2.2
Name: bangla-ipa
Version: 1.0.2
Summary: A Python module for generating Bangla IPA transliterations.
Home-page: https://github.com/bipsec/bangla-ipa
Author: Biplab Kumar Sarkar, Afrar Jahin, Asif Shusmit
Author-email: bip.sec22@gmail.com
License: MIT
Keywords: python,IPA,Bangla IPA,International Phonetic Alphabet,Bangla linguistics,transliteration
Classifier: Development Status :: 4 - Beta
Classifier: Intended Audience :: Developers
Classifier: License :: OSI Approved :: MIT License
Classifier: Programming Language :: Python :: 3
Classifier: Programming Language :: Python :: 3.6
Classifier: Programming Language :: Python :: 3.7
Classifier: Programming Language :: Python :: 3.8
Classifier: Programming Language :: Python :: 3.9
Classifier: Operating System :: OS Independent
Classifier: Topic :: Software Development :: Libraries :: Python Modules
Requires-Python: >=3.6
License-File: LICENSE
Requires-Dist: certifi==2024.12.14
Requires-Dist: charset-normalizer==3.4.1
Requires-Dist: colorama==0.4.6
Requires-Dist: docutils==0.21.2
Requires-Dist: filelock==3.17.0
Requires-Dist: fsspec==2024.12.0
Requires-Dist: id==1.5.0
Requires-Dist: idna==3.10
Requires-Dist: jaraco.classes==3.4.0
Requires-Dist: jaraco.context==6.0.1
Requires-Dist: jaraco.functools==4.1.0
Requires-Dist: Jinja2==3.1.5
Requires-Dist: keyring==25.6.0
Requires-Dist: markdown-it-py==3.0.0
Requires-Dist: MarkupSafe==3.0.2
Requires-Dist: mdurl==0.1.2
Requires-Dist: more-itertools==10.6.0
Requires-Dist: mpmath==1.3.0
Requires-Dist: networkx==3.4.2
Requires-Dist: nh3==0.2.20
Requires-Dist: numpy==2.2.2
Requires-Dist: packaging==24.2
Requires-Dist: pandas==2.2.3
Requires-Dist: Pygments==2.19.1
Requires-Dist: python-dateutil==2.9.0.post0
Requires-Dist: pytz==2024.2
Requires-Dist: pywin32-ctypes==0.2.3
Requires-Dist: readme_renderer==44.0
Requires-Dist: requests==2.32.3
Requires-Dist: requests-toolbelt==1.0.0
Requires-Dist: rfc3986==2.0.0
Requires-Dist: rich==13.9.4
Requires-Dist: sentencepiece==0.2.0
Requires-Dist: setuptools==75.8.0
Requires-Dist: six==1.17.0
Requires-Dist: sympy==1.13.3
Requires-Dist: torch==2.4.1
Requires-Dist: torchdata==0.7.1
Requires-Dist: torchtext==0.6.0
Requires-Dist: tqdm==4.67.1
Requires-Dist: twine==6.1.0
Requires-Dist: typing_extensions==4.12.2
Requires-Dist: tzdata==2025.1
Requires-Dist: urllib3==2.3.0
Requires-Dist: wheel==0.45.1
Dynamic: author
Dynamic: author-email
Dynamic: classifier
Dynamic: description
Dynamic: description-content-type
Dynamic: home-page
Dynamic: keywords
Dynamic: license
Dynamic: requires-dist
Dynamic: requires-python
Dynamic: summary
